dydns.py
dyDNS-0.0.12.dist-info/METADATA
dyDNS-0.0.12.dist-info/WHEEL
dyDNS-0.0.12.dist-info/entry_points.txt
dyDNS-0.0.12.dist-info/top_level.txt
dyDNS-0.0.12.dist-info/RECORD
