Metadata-Version: 2.1
Name: dyDNS
Version: 0.0.12
Summary: activating dynamicDNS for freedns.afraid.org
Home-page: https://github.com/y-takefuji/dyDNS
Author: yoshiyasu takefuji
Author-email: takefuji@keio.jp
License: UNKNOWN
Project-URL: Bug Tracker, https://github.com/y-takefuji/dyDNS
Platform: UNKNOWN
Classifier: Programming Language :: Python :: 3
Classifier: License :: OSI Approved :: MIT License
Classifier: Operating System :: OS Independent
Requires-Python: >=3.8
